shamim_humans/__init__.py
shamim_humans-0.0.1.dist-info/METADATA
shamim_humans-0.0.1.dist-info/WHEEL
shamim_humans-0.0.1.dist-info/licenses/LICENSE
shamim_humans-0.0.1.dist-info/RECORD
