Metadata-Version: 2.4
Name: shamim_humans
Version: 0.0.1
Summary: collection of biblical humans and their family relations
Project-URL: Homepage, https://github.com/nbrshamim/humans
Project-URL: Issues, https://github.com/nbrshamim/humans
Author-email: "Md.Shamim-Ul-Islam" <nbrshamim@gmail.com>
License-File: LICENSE
Classifier: License :: OSI Approved :: GNU General Public License v3 (GPLv3)
Classifier: Operating System :: OS Independent
Classifier: Programming Language :: Python :: 3
Requires-Python: >=3.8
